pytest_imports/__init__.py
shishito/__init__.py
shishito/cli.py
shishito/shishito_runner.py
shishito/conf/__init__.py
shishito/conf/conftest.py
shishito/reporting/__init__.py
shishito/reporting/junithtml.py
shishito/reporting/reporter.py
shishito/reporting/resources/CombinedReportTemplate.html
shishito/reporting/resources/combined_report.js
shishito/reporting/resources/jquery.js
shishito/reporting/resources/main.js
shishito/reporting/resources/style.css
shishito/runtime/__init__.py
shishito/runtime/all_content_type.py
shishito/runtime/shishito_support.py
shishito/runtime/environment/__init__.py
shishito/runtime/environment/appium.py
shishito/runtime/environment/appium_bs.py
shishito/runtime/environment/browserstack.py
shishito/runtime/environment/local.py
shishito/runtime/environment/node_webkit.py
shishito/runtime/environment/remote.py
shishito/runtime/environment/shishito.py
shishito/runtime/platform/__init__.py
shishito/runtime/platform/shishito_control_test.py
shishito/runtime/platform/shishito_execution.py
shishito/runtime/platform/generic/__init__.py
shishito/runtime/platform/generic/control_execution.py
shishito/runtime/platform/generic/control_test.py
shishito/runtime/platform/mobile/__init__.py
shishito/runtime/platform/mobile/control_execution.py
shishito/runtime/platform/mobile/control_test.py
shishito/runtime/platform/node_webkit/__init__.py
shishito/runtime/platform/node_webkit/control_execution.py
shishito/runtime/platform/node_webkit/control_test.py
shishito/runtime/platform/web/__init__.py
shishito/runtime/platform/web/control_execution.py
shishito/runtime/platform/web/control_test.py
shishito/services/__init__.py
shishito/services/browserstack.py
shishito/services/circle_ci.py
shishito/services/email_imap.py
shishito/services/jira_zephyr_api.py
shishito/services/qastats_api.py
shishito/services/testrail_api.py
shishito/ui/__init__.py
shishito/ui/auth.py
shishito/ui/ripple.py
shishito/ui/selenium_support.py
shishito-3.1.16.data/scripts/shi
shishito-3.1.16.dist-info/LICENSE
shishito-3.1.16.dist-info/METADATA
shishito-3.1.16.dist-info/WHEEL
shishito-3.1.16.dist-info/entry_points.txt
shishito-3.1.16.dist-info/top_level.txt
shishito-3.1.16.dist-info/RECORD
